CREDITS.md
LICENSE.txt
MANIFEST.in
README.md
setup.py
PySciMath/Arithmetic.py
PySciMath/Geometry.py
PySciMath/Graphs.py
PySciMath/Quadratic.py
PySciMath/Statistics.py
PySciMath/Trigonometry.py
PySciMath/__init__.py
PySciMath.egg-info/PKG-INFO
PySciMath.egg-info/SOURCES.txt
PySciMath.egg-info/dependency_links.txt
PySciMath.egg-info/requires.txt
PySciMath.egg-info/top_level.txt