Metadata-Version: 2.1
Name: PySciMath
Version: 1.5.7
Summary: PySciMath is a general-purpose Python package to work on calculations and solve mathmematical and scientific problems.
Home-page: https://github.com/Anikethc/PySciMath
Download-URL: https://pypi.org/project/PySciMath
Author: Aniketh Chavare
Author-email: anikethchavare@outlook.com
License: MIT
Keywords: Math,Mathematics,Science,Calculations
License-File: LICENSE.txt
